sphinx_ioam_theme/__init__.py
sphinx_ioam_theme/_version.py
sphinx_ioam_theme/layout.html
sphinx_ioam_theme/search.html
sphinx_ioam_theme/theme.conf
sphinx_ioam_theme/includes/ga.html
sphinx_ioam_theme/includes/searchbox.html
sphinx_ioam_theme/static/css/main.css
sphinx_ioam_theme/static/images/favicon.ico
sphinx_ioam_theme/static/images/logo.png
sphinx_ioam_theme/static/js/main.js
sphinx_ioam_theme-0.1.1.dist-info/METADATA
sphinx_ioam_theme-0.1.1.dist-info/RECORD
sphinx_ioam_theme-0.1.1.dist-info/WHEEL
sphinx_ioam_theme-0.1.1.dist-info/entry_points.txt
sphinx_ioam_theme-0.1.1.dist-info/top_level.txt
