Metadata-Version: 2.1
Name: sphinx-ioam-theme
Version: 0.1.1
Summary: For nbsite
Home-page: https://github.com/ioam/sphinx_ioam_theme
License: BSD-3
Platform: UNKNOWN
Requires-Python: >=2.7
Requires-Dist: sphinx
